banc/__init__.py
banc/annotations.py
banc/auth.py
banc/connectivity.py
banc/lookup.py
banc/ngl_info.py
banc/publish.py
banc/render_neurons.py
banc/skeletonize.py
banc/statebuilder.py
banc/statemanager.py
banc/synaptic_links.py
banc/template_spaces.py
banc/upload.py
banc/visualize.py
banc/transforms/__init__.py
banc/transforms/realignment.py
banc/transforms/template_alignment.py
banc-0.5.3.dist-info/licenses/LICENSE
banc-0.5.3.dist-info/METADATA
banc-0.5.3.dist-info/WHEEL
banc-0.5.3.dist-info/top_level.txt
banc-0.5.3.dist-info/RECORD
