Metadata-Version: 2.4
Name: banc
Version: 0.5.3
Summary: Tools for the GridTape-TEM dataset of an adult female fly's Brain And Nerve Cord
Author-email: Jasper Phelps <jasper.s.phelps@gmail.com>
License:                     GNU GENERAL PUBLIC LICENSE
Project-URL: Repository, https://github.com/jasper-tms/the-BANC-fly-connectome
Keywords: neuroscience,connectomics,Drosophila,fruit fly,brain,VNC
Classifier: Programming Language :: Python :: 3
Classifier: Operating System :: OS Independent
Classifier: License :: OSI Approved :: GNU General Public License v3 or later (GPLv3+)
Classifier: Development Status :: 4 - Beta
Classifier: Intended Audience :: Science/Research
Classifier: Topic :: Scientific/Engineering :: Bio-Informatics
Requires-Python: >=3.6
License-File: LICENSE
Requires-Dist: numpy
Requires-Dist: matplotlib
Requires-Dist: cloud-volume
Requires-Dist: python-catmaid
Requires-Dist: meshparty
Requires-Dist: navis
Requires-Dist: flybrains
Requires-Dist: transformix
Requires-Dist: nglui
Requires-Dist: pyperclip
Requires-Dist: numpyimage
Requires-Dist: pandas
Requires-Dist: connected-components-3d
Requires-Dist: fill_voids
Requires-Dist: task-queue
Requires-Dist: caveclient
Requires-Dist: cloud-files
Requires-Dist: urllib3
Requires-Dist: trimesh
Requires-Dist: pcg_skel
Requires-Dist: anytree
Dynamic: license-file
